pkgps-1.0.1.dist-info/METADATA
pkgps-1.0.1.dist-info/WHEEL
pkgps-1.0.1.dist-info/entry_points.txt
pkgps/__init__.py
pkgps/_impl/__init__.py
pkgps/_impl/attrs/__init__.py
pkgps/_impl/attrs/nevr.py
pkgps/_impl/attrs/nevra.py
pkgps/_impl/attrs/nvr.py
pkgps/_impl/attrs/nvra.py
pkgps/_impl/exc.py
pkgps/_impl/nevr.py
pkgps/_impl/nevra.py
pkgps/_impl/nvr.py
pkgps/_impl/nvra.py
pkgps/_impl/parse.py
pkgps/_impl/pydantic/__init__.py
pkgps/_impl/pydantic/ext.py
pkgps/_impl/pydantic/nevr.py
pkgps/_impl/pydantic/nevra.py
pkgps/_impl/pydantic/nvr.py
pkgps/_impl/pydantic/nvra.py
pkgps/attrs.py
pkgps/py.typed
pkgps/pydantic.py
pkgps/version.py
pkgps-1.0.1.dist-info/RECORD
