Metadata-Version: 2.1
Name: pkgps
Version: 1.0.1
Summary: Package coordinates as types.
Author-Email: Ryan Smith <ryan.d.smith.106@gmail.com>
License: MIT
Requires-Python: >=3.10
Requires-Dist: collektions>=1.1.1
Provides-Extra: pydantic
Requires-Dist: pydantic; extra == "pydantic"
Requires-Dist: typing-extensions; python_version < "3.13" and extra == "pydantic"
Provides-Extra: attrs
Requires-Dist: attrs; extra == "attrs"
Provides-Extra: all
Requires-Dist: attrs; extra == "all"
Requires-Dist: pydantic; extra == "all"
